json_build/__init__.py
json_build/build.py
json_build-1.0.4.dist-info/LICENSE
json_build-1.0.4.dist-info/METADATA
json_build-1.0.4.dist-info/WHEEL
json_build-1.0.4.dist-info/top_level.txt
json_build-1.0.4.dist-info/RECORD
