Metadata-Version: 2.1
Name: json-build
Version: 1.0.4
Summary: JSON file builder
Author: Vince Berry
Author-email: vincent.berry11@gmail.com
Keywords: python,json,build,config
Classifier: Development Status :: 1 - Planning
Classifier: Intended Audience :: Developers
Classifier: Programming Language :: Python :: 3
Classifier: Operating System :: Unix
Classifier: Operating System :: MacOS :: MacOS X
Classifier: Operating System :: Microsoft :: Windows
License-File: LICENSE
